shittier-0.1.2.dist-info/licenses/LICENCE
src/__init__.py
src/language_transformers.py
src/transformer.py
src/transformer_libcst.py
src/utils.py
tests/__init__.py
shittier-0.1.2.dist-info/METADATA
shittier-0.1.2.dist-info/WHEEL
shittier-0.1.2.dist-info/entry_points.txt
shittier-0.1.2.dist-info/top_level.txt
shittier-0.1.2.dist-info/RECORD
